napari_k2_wavebreaker/ClickLabel.py
napari_k2_wavebreaker/__init__.py
napari_k2_wavebreaker/_widget.py
napari_k2_wavebreaker/autocorrelation.py
napari_k2_wavebreaker/crosscorrelation.py
napari_k2_wavebreaker/functions.py
napari_k2_wavebreaker/napari.yaml
napari_k2_wavebreaker/_tests/__init__.py
napari_k2_wavebreaker/_tests/test_widget.py
napari_k2_wavebreaker/static/auto_F.png
napari_k2_wavebreaker/static/auto_T.png
napari_k2_wavebreaker/static/compas.svg
napari_k2_wavebreaker/static/cross_F.png
napari_k2_wavebreaker/static/cross_T.png
napari_k2_wavebreaker/static/form.ui
napari_k2_wavebreaker/static/logo.png
napari_k2_WaveBreaker-0.2.5.dist-info/LICENSE
napari_k2_WaveBreaker-0.2.5.dist-info/METADATA
napari_k2_WaveBreaker-0.2.5.dist-info/WHEEL
napari_k2_WaveBreaker-0.2.5.dist-info/entry_points.txt
napari_k2_WaveBreaker-0.2.5.dist-info/top_level.txt
napari_k2_WaveBreaker-0.2.5.dist-info/RECORD
